dictdot/__init__.py
dictdot-1.5.1.dist-info/LICENSE
dictdot-1.5.1.dist-info/METADATA
dictdot-1.5.1.dist-info/WHEEL
dictdot-1.5.1.dist-info/top_level.txt
dictdot-1.5.1.dist-info/RECORD
