Metadata-Version: 2.1
Name: dictdot
Version: 1.5.1
Summary: Python dict accessible by dot.
Home-page: https://github.com/nchz/dictdot
Author: nchz
Requires-Python: >=3.7
License-File: LICENSE
